{
    "Version": "1.0.0.0",
    "LastState": 3,
    "Modules": [
        {
            "ModuleName": "Front Left",
            "ModuleId": 0,
            "Encoder": {
                "Id": 4,
                "Name": "CANCoder (Device ID 4)",
                "Model": "CANCoder",
                "CANbus": "rio",
                "CANbusFriendly": "",
                "SelectedMotorType": null,
                "IsStandaloneFx": false
            },
            "SteerMotor": {
                "Id": 42,
                "Name": "Front Left Steering Motor",
                "Model": "Talon FX",
                "CANbus": "rio",
                "CANbusFriendly": "",
                "SelectedMotorType": {
                    "Name": "WCP Kraken x60",
                    "FreeSpeedRps": 96.7,
                    "SlipCurrentLimit": 120,
                    "StatorCurrentLimit": 60
                },
                "IsStandaloneFx": false
            },
            "DriveMotor": {
                "Id": 41,
                "Name": "Front Left (Device ID 41)",
                "Model": "Talon FX vers. C",
                "CANbus": "rio",
                "CANbusFriendly": "",
                "SelectedMotorType": {
                    "Name": "WCP Kraken x60",
                    "FreeSpeedRps": 96.7,
                    "SlipCurrentLimit": 120,
                    "StatorCurrentLimit": 60
                },
                "IsStandaloneFx": false
            },
            "IsEncoderInverted": false,
            "IsSteerInverted": false,
            "SelectedEncoderType": "CANcoder",
            "EncoderOffset": 0.0,
            "DriveMotorSelectionState": 1,
            "SteerMotorSelectionState": 1,
            "SteerEncoderSelectionState": 1,
            "IsModuleValidationComplete": true,
            "ValidatedSteerId": 42,
            "ValidatedDriveId": 41,
            "ValidatedEncoderId": 4
        },
        {
            "ModuleName": "Front Right",
            "ModuleId": 1,
            "Encoder": {
                "Id": 1,
                "Name": "CANCoder (Device ID 1)",
                "Model": "CANCoder",
                "CANbus": "rio",
                "CANbusFriendly": "",
                "SelectedMotorType": null,
                "IsStandaloneFx": false
            },
            "SteerMotor": {
                "Id": 12,
                "Name": "Front Right Steering Motor",
                "Model": "Talon FX",
                "CANbus": "rio",
                "CANbusFriendly": "",
                "SelectedMotorType": {
                    "Name": "WCP Kraken x60",
                    "FreeSpeedRps": 96.7,
                    "SlipCurrentLimit": 120,
                    "StatorCurrentLimit": 60
                },
                "IsStandaloneFx": false
            },
            "DriveMotor": {
                "Id": 11,
                "Name": "Front Right (Device ID 11)",
                "Model": "Talon FX vers. C",
                "CANbus": "rio",
                "CANbusFriendly": "",
                "SelectedMotorType": {
                    "Name": "WCP Kraken x60",
                    "FreeSpeedRps": 96.7,
                    "SlipCurrentLimit": 120,
                    "StatorCurrentLimit": 60
                },
                "IsStandaloneFx": false
            },
            "IsEncoderInverted": false,
            "IsSteerInverted": false,
            "SelectedEncoderType": "CANcoder",
            "EncoderOffset": 0.0,
            "DriveMotorSelectionState": 1,
            "SteerMotorSelectionState": 1,
            "SteerEncoderSelectionState": 1,
            "IsModuleValidationComplete": true,
            "ValidatedSteerId": 12,
            "ValidatedDriveId": 11,
            "ValidatedEncoderId": 1
        },
        {
            "ModuleName": "Back Left",
            "ModuleId": 2,
            "Encoder": {
                "Id": 3,
                "Name": "CANCoder (Device ID 3)",
                "Model": "CANCoder",
                "CANbus": "rio",
                "CANbusFriendly": "",
                "SelectedMotorType": null,
                "IsStandaloneFx": false
            },
            "SteerMotor": {
                "Id": 32,
                "Name": "Back Left Steering",
                "Model": "Talon FX",
                "CANbus": "rio",
                "CANbusFriendly": "",
                "SelectedMotorType": {
                    "Name": "WCP Kraken x60",
                    "FreeSpeedRps": 96.7,
                    "SlipCurrentLimit": 120,
                    "StatorCurrentLimit": 60
                },
                "IsStandaloneFx": false
            },
            "DriveMotor": {
                "Id": 31,
                "Name": "Back Left (Device ID 31)",
                "Model": "Talon FX vers. C",
                "CANbus": "rio",
                "CANbusFriendly": "",
                "SelectedMotorType": {
                    "Name": "WCP Kraken x60",
                    "FreeSpeedRps": 96.7,
                    "SlipCurrentLimit": 120,
                    "StatorCurrentLimit": 60
                },
                "IsStandaloneFx": false
            },
            "IsEncoderInverted": false,
            "IsSteerInverted": false,
            "SelectedEncoderType": "CANcoder",
            "EncoderOffset": 0.0,
            "DriveMotorSelectionState": 1,
            "SteerMotorSelectionState": 1,
            "SteerEncoderSelectionState": 1,
            "IsModuleValidationComplete": true,
            "ValidatedSteerId": 32,
            "ValidatedDriveId": 31,
            "ValidatedEncoderId": 3
        },
        {
            "ModuleName": "Back Right",
            "ModuleId": 3,
            "Encoder": {
                "Id": 2,
                "Name": "CANCoder (Device ID 2)",
                "Model": "CANCoder",
                "CANbus": "rio",
                "CANbusFriendly": "",
                "SelectedMotorType": null,
                "IsStandaloneFx": false
            },
            "SteerMotor": {
                "Id": 22,
                "Name": "Back Right Steering Motor",
                "Model": "Talon FX",
                "CANbus": "rio",
                "CANbusFriendly": "",
                "SelectedMotorType": {
                    "Name": "WCP Kraken x60",
                    "FreeSpeedRps": 96.7,
                    "SlipCurrentLimit": 120,
                    "StatorCurrentLimit": 60
                },
                "IsStandaloneFx": false
            },
            "DriveMotor": {
                "Id": 21,
                "Name": "Back Right (Device ID 21)",
                "Model": "Talon FX vers. C",
                "CANbus": "rio",
                "CANbusFriendly": "",
                "SelectedMotorType": {
                    "Name": "WCP Kraken x60",
                    "FreeSpeedRps": 96.7,
                    "SlipCurrentLimit": 120,
                    "StatorCurrentLimit": 60
                },
                "IsStandaloneFx": false
            },
            "IsEncoderInverted": false,
            "IsSteerInverted": false,
            "SelectedEncoderType": "CANcoder",
            "EncoderOffset": 0.0,
            "DriveMotorSelectionState": 1,
            "SteerMotorSelectionState": 1,
            "SteerEncoderSelectionState": 1,
            "IsModuleValidationComplete": true,
            "ValidatedSteerId": 22,
            "ValidatedDriveId": 21,
            "ValidatedEncoderId": 2
        }
    ],
    "SwerveOptions": {
        "kSpeedAt12Volts": 5.101280870666283,
        "Gyro": null,
        "IsValidGyroCANbus": false,
        "VerticalTrackSizeInches": 18.75,
        "HorizontalTrackSizeInches": 18.75,
        "WheelRadiusInches": 1.957,
        "IsLeftSideInverted": false,
        "IsRightSideInverted": true,
        "SwerveModuleType": 4,
        "SwerveModuleConfiguration": {
            "ModuleBrand": 4,
            "DriveRatio": 6.122448979591837,
            "SteerRatio": 21.428571428571427,
            "CouplingRatio": 3.5714285714285716,
            "CustomName": "L3"
        },
        "HasVerifiedSteer": false,
        "SelectedModuleManufacturer": "Swerve Drive Specialties (SDS)",
        "HasVerifiedDrive": false,
        "IsValidConfiguration": true
    }
}